[
    {
        "장비": "2성",
        "성공률": "80%",
        "재료": [
            "1성,",
            "자연의심장,",
            "작은정령의보석10"
        ]
    },
    {
        "장비": "3성",
        "성공률": "50%",
        "재료": [
            "2성,",
            "자연의심장,",
            "작은정령의보석20,",
            "커다란정령의보석"
        ]
    },
    {
        "장비": "4성",
        "성공률": "50%",
        "재료": [
            "3성,",
            "자연의심장2,",
            "작은정령의보석20,",
            "커다란정령의보석2"
        ]
    },
    {
        "장비": "5성",
        "성공률": "20%",
        "재료": [
            "4성,",
            "작은정령의보석30,",
            "커다란정령의보석3,",
            "강렬한정령의보석1"
        ]
    },
    {
        "장비": "6성",
        "성공률": "20%",
        "재료": [
            "5성,",
            "작은정령의보석30,",
            "커다란정령의보석3,",
            "강렬한정령의보석2"
        ]
    },
    {
        "장비": "7성",
        "성공률": "10%",
        "재료": [
            "6성,",
            "작은정령의보석30,",
            "커다란정령의보석3,",
            "강렬한정령의보석3,",
            "불멸정령의보석"
        ]
    },
    {
        "장비": "생명의목걸이",
        "성공률": "25%",
        "재료": [
            "자연의심장,",
            "커다란정령의보석"
        ]
    },
    {
        "장비": "커다란생명의목걸이",
        "성공률": "15%",
        "재료": [
            "생명의목걸이,",
            "커다란정령의보석3,",
            "강렬한정령의보석"
        ]
    },
    {
        "장비": "극락의목걸이",
        "성공률": "10%",
        "재료": [
            "커다란생명의목걸이,",
            "커다란정령의보석5,",
            "강렬한정령의보석3,",
            "불멸정령의보석"
        ]
    },
    {
        "장비": "신물2성",
        "성공률": "100%",
        "재료": [
            "신물1성2"
        ]
    },
    {
        "장비": "신물3성",
        "성공률": "100%",
        "재료": [
            "신물2성,",
            "신물1성"
        ]
    },
    {
        "장비": "신물4성",
        "성공률": "100%",
        "재료": [
            "신물3성,",
            "신물1성,",
            "불멸의신물10"
        ]
    },
    {
        "장비": "성물'진",
        "성공률": "10%",
        "재료": [
            "성물,",
            "자연의심장,",
            "불멸의신물,",
            "XX의멸"
        ]
    },
    {
        "장비": "문양'진",
        "성공률": "10%",
        "재료": [
            "문양,",
            "자연의심장10,",
            "작은정령의보석10,",
            "커다란정령의보석5,",
            "강렬한정령의보석3,",
            "불멸정령의보석"
        ]
    }
]