{
    "새끼줄": [
        "보리볏짚",
        2,
        "볏짚",
        2
    ],
    "삼베천": [
        "새끼줄",
        1,
        "삼베실",
        1
    ],
    "황저포": [
        "삼베천",
        1,
        "황마실",
        2
    ],
    "경원장갑": [
        "황저포",
        1,
        "연옥가루",
        1,
        "경원의문장",
        1,
        "곰가죽",
        5
    ],
    "경원팔찌": [
        "황저포",
        1,
        "화살통나무",
        2,
        "경원의문장",
        1,
        "곰가죽",
        5
    ],
    "경원반지": [
        "황저포",
        1,
        "연옥석",
        2,
        "경원의문장",
        1,
        "곰가죽",
        5
    ],
    "경원선류": [
        "황저포",
        1,
        "쑥가루",
        1,
        "경원의문장",
        1,
        "곰가죽",
        5
    ],
    "경원깍지": [
        "황저포",
        1,
        "삼통나무",
        2,
        "경원의문장",
        1,
        "곰가죽",
        5
    ],
    "경원천인반지": [
        "황저포",
        1,
        "연옥석",
        1,
        "경원의문장",
        1,
        "곰가죽",
        5
    ],
    "경원마도반지": [
        "황저포",
        1,
        "쑥가루",
        1,
        "경원의문장",
        1,
        "곰가죽",
        5
    ],
    "경원염주": [
        "황저포",
        1,
        "쑥가루",
        1,
        "경원의문장",
        1,
        "곰가죽",
        5
    ],
    "경원보호대": [
        "황저포",
        1,
        "쑥가루",
        1,
        "경원의문장",
        1,
        "곰가죽",
        5
    ],
    "경원투수": [
        "황저포",
        1,
        "쑥가루",
        1,
        "경원의문장",
        1,
        "곰가죽",
        5
    ],
    "아마천": [
        "황저포",
        1,
        "아마실",
        3
    ],
    "사군자6폭병풍": [
        "아마천",
        1,
        "중급소나무판자",
        1,
        "아교",
        1
    ],
    "곤지": [
        "쪽꽃",
        1,
        "빛나는돌가루",
        2,
        "황마잎",
        2
    ],
    "모시천": [
        "아마천",
        1,
        "모시실",
        4
    ],
    "반창고": [
        "중급아마천",
        2,
        "아마실",
        2,
        "쑥가루",
        2
    ],
    "신선도6폭병풍": [
        "모시천",
        1,
        "중급은행나무판자",
        1,
        "청동결정",
        1,
        "아교",
        1
    ],
    "파천장갑": [
        "경원장갑",
        1,
        "모시천",
        2,
        "구리조각",
        1,
        "파천의문장",
        1,
        "게등껍질",
        5
    ],
    "파천팔찌": [
        "경원팔찌",
        1,
        "모시천",
        2,
        "중급대나무판자",
        1,
        "파천의문장",
        1,
        "문어의심장",
        1
    ],
    "파천반지": [
        "경원반지",
        1,
        "중급아마천",
        2,
        "중급대나무판자",
        1,
        "파천의문장",
        1,
        "연옥",
        1,
        "게등껍질",
        5
    ],
    "파천선류": [
        "경원선류",
        1,
        "중급아마천",
        2,
        "중급모시천",
        1,
        "파천의문장",
        1,
        "문어의심장",
        1
    ],
    "파천깍지": [
        "경원깍지",
        1,
        "대나무판자",
        2,
        "구리조각",
        1,
        "파천의문장",
        1,
        "연옥",
        1,
        "게등껍질",
        5
    ],
    "파천천인반지": [
        "경원천인반지",
        1,
        "중급아마천",
        2,
        "중급대나무판자",
        1,
        "파천의문장",
        1,
        "연옥",
        1,
        "게등껍질",
        5
    ],
    "파천마도반지": [
        "경원마도반지",
        1,
        "중급아마천",
        2,
        "중급모시천",
        1,
        "파천의문장",
        1,
        "문어의심장",
        1
    ],
    "파천염주": [
        "경원염주",
        1,
        "중급아마천",
        2,
        "중급모시천",
        1,
        "파천의문장",
        1,
        "문어의심장",
        1
    ],
    "파천보호대": [
        "경원보호대",
        1,
        "중급아마천",
        2,
        "중급대나무판자",
        1,
        "파천의문장",
        1,
        "연옥",
        1,
        "게등껍질",
        5
    ],
    "파천투수": [
        "경원투수",
        1,
        "중급아마천",
        2,
        "중급대나무판자",
        1,
        "파천의문장",
        1,
        "연옥",
        1,
        "게등껍질",
        5
    ],
    "무명천": [
        "모시천",
        1,
        "무명실",
        5
    ],
    "꽃무늬복면": [
        "쪽꽃",
        1,
        "황마꽃",
        1,
        "중급모시천",
        2,
        "적옥",
        1,
        "적옥가루",
        2
    ],
    "양모천": [
        "무명천",
        1,
        "양모실",
        5
    ],
    "복면": [
        "양모천",
        2,
        "강철쇠조각",
        1,
        "떡갈나무잎",
        2,
        "도삭산묘피",
        1
    ],
    "연꽃화관": [
        "상급대나무판자",
        1,
        "무명천",
        3,
        "영지버섯",
        2,
        "연꽃",
        1
    ],
    "비단": [
        "양모천",
        1,
        "명주실",
        5
    ],
    "금강장갑": [
        "파천장갑",
        1,
        "중급양모천",
        2,
        "은괴",
        2,
        "금강의문장",
        1,
        "반송잎",
        1,
        "백현목",
        1
    ],
    "금강팔찌": [
        "파천팔찌",
        1,
        "비단",
        2,
        "강철쇠조각",
        2,
        "금강의문장",
        1,
        "산인삼잎",
        1,
        "백현목",
        1
    ],
    "금강반지": [
        "파천반지",
        1,
        "중급양모천",
        2,
        "은괴",
        2,
        "금강의문장",
        1,
        "산인삼잎",
        1,
        "자현목",
        1
    ],
    "금강선류": [
        "파천선류",
        1,
        "비단",
        2,
        "중급반송판자",
        2,
        "금강의문장",
        1,
        "반송잎",
        1,
        "자현목",
        1
    ],
    "금강깍지": [
        "파천깍지",
        1,
        "중급양모천",
        2,
        "금강송판자",
        2,
        "금강의문장",
        1,
        "백현목",
        1
    ],
    "금강천인반지": [
        "파천천인반지",
        1,
        "중급양모천",
        2,
        "은괴",
        2,
        "금강의문장",
        1,
        "산인삼잎",
        1,
        "자현목",
        1
    ],
    "금강마도반지": [
        "파천마도반지",
        1,
        "중급양모천",
        2,
        "은괴",
        2,
        "금강의문장",
        1,
        "반송잎",
        1,
        "자현목",
        1
    ],
    "금강염주": [
        "파천염주",
        1,
        "중급양모천",
        2,
        "은괴",
        2,
        "금강의문장",
        1,
        "반송잎",
        1,
        "자현목",
        1
    ],
    "금강보호대": [
        "파천보호대",
        1,
        "중급양모천",
        2,
        "은괴",
        2,
        "금강의문장",
        1,
        "산인삼잎",
        1,
        "자현목",
        1
    ],
    "금강투수": [
        "파천투수",
        1,
        "중급양모천",
        2,
        "은괴",
        2,
        "금강의문장",
        1,
        "산인삼잎",
        1,
        "자현목",
        1
    ],
    "사각복면": [
        "중급비단",
        2,
        "백옥",
        2,
        "은광결정",
        2,
        "산양삼잎",
        2
    ],
    "오봉산도6폭병풍": [
        "비단",
        2,
        "아교",
        1,
        "중급은괴",
        2,
        "청옥가루",
        2,
        "적옥가루",
        2
    ],
    "바람제일식장갑": [
        "금강장갑",
        1,
        "상급비단",
        3,
        "상급무명천",
        3,
        "바람의문장",
        1,
        "황금호박",
        10,
        "황금조각",
        1
    ],
    "바람제일식팔찌": [
        "금강팔찌",
        1,
        "상급비단",
        3,
        "상급떡갈나무판자",
        3,
        "바람의문장",
        1,
        "황금호박",
        10,
        "황금실",
        1
    ],
    "바람제일식반지": [
        "금강반지",
        1,
        "상급비단",
        3,
        "상급강철괴",
        3,
        "바람의문장",
        1,
        "황금호박",
        10,
        "천금조각",
        1
    ],
    "바람제일식선류": [
        "금강선류",
        1,
        "상급비단",
        3,
        "상급강철괴",
        3,
        "바람의문장",
        1,
        "황금호박",
        10,
        "황금실",
        1
    ],
    "바람제일식깍지": [
        "금강깍지",
        1,
        "상급비단",
        3,
        "상급떡갈나무판자",
        3,
        "바람의문장",
        1,
        "황금호박",
        10,
        "황금조각",
        1
    ],
    "바람제일식천인반지": [
        "금강천인반지",
        1,
        "상급비단",
        3,
        "상급강철괴",
        3,
        "바람의문장",
        1,
        "황금호박",
        10,
        "황금실",
        1
    ],
    "바람제일식마도반지": [
        "금강마도반지",
        1,
        "상급비단",
        3,
        "상급강철괴",
        3,
        "바람의문장",
        1,
        "황금호박",
        10,
        "천금조각",
        1
    ],
    "바람제일식염주": [
        "금강염주",
        1,
        "상급비단",
        3,
        "상급강철괴",
        3,
        "바람의문장",
        1,
        "황금호박",
        10,
        "황금실",
        1
    ],
    "바람제일식보호대": [
        "금강보호대",
        1,
        "상급비단",
        3,
        "상급강철괴",
        3,
        "바람의문장",
        1,
        "황금호박",
        10,
        "천금조각",
        1
    ],
    "바람제일식투수": [
        "금강투수",
        1,
        "상급비단",
        3,
        "상급강철괴",
        3,
        "바람의문장",
        1,
        "황금호박",
        10,
        "천금조각",
        1
    ],
    "황금비단": [
        "상급비단",
        1,
        "고운금가루",
        3
    ],
    "바람제영식장갑": [
        "바람홍옥장갑",
        1,
        "황금비단",
        3,
        "묵철가루",
        10,
        "태풍의문장",
        1
    ],
    "바람제영식팔찌": [
        "바람홍옥팔찌",
        1,
        "황금비단",
        3,
        "홍염의결정",
        3,
        "태풍의문장",
        1
    ],
    "바람제영식반지": [
        "바람홍옥반지",
        1,
        "황금비단",
        3,
        "환혼의물약",
        3,
        "태풍의문장",
        1
    ],
    "바람제영식선류": [
        "바람홍옥선류",
        1,
        "황금비단",
        3,
        "환혼의물약",
        3,
        "태풍의문장",
        1
    ],
    "바람제영식깍지": [
        "바람홍옥깍지",
        1,
        "황금비단",
        3,
        "홍염의결정",
        3,
        "태풍의문장",
        1
    ],
    "바람제영식천인반지": [
        "바람홍옥천인반지",
        1,
        "황금비단",
        3,
        "환혼의물약",
        3,
        "태풍의문장",
        1
    ],
    "바람제영식마도반지": [
        "바람홍옥마도반지",
        1,
        "황금비단",
        3,
        "환혼의물약",
        3,
        "태풍의문장",
        1
    ],
    "바람제영식염주": [
        "바람홍옥염주",
        1,
        "황금비단",
        3,
        "환혼의물약",
        3,
        "태풍의문장",
        1
    ],
    "바람제영식보호대": [
        "바람홍옥보호대",
        1,
        "황금비단",
        3,
        "환혼의물약",
        3,
        "태풍의문장",
        1
    ],
    "바람제영식투수": [
        "바람홍옥투수",
        1,
        "황금비단",
        3,
        "환혼의물약",
        3,
        "태풍의문장",
        1
    ],
    "삼베실": [
        "삼통나무",
        2
    ],
    "화살나무판자": [
        "삼베실",
        1,
        "화살통나무",
        1
    ],
    "소나무판자": [
        "화살나무판자",
        1,
        "소나무쪽",
        2
    ],
    "밀짚모자": [
        "중급삼나무판자",
        1,
        "쪽잎",
        1,
        "중급새끼줄",
        1
    ],
    "경원투구": [
        "중급소나무판자",
        1,
        "빛나는돌가루",
        1,
        "경원의문장",
        1,
        "숲돼지고기",
        5
    ],
    "은행나무판자": [
        "소나무판자",
        1,
        "은행통나무",
        3
    ],
    "족제비수염": [
        "은행나무판자",
        1,
        "상급삼베천",
        1,
        "곡물가루",
        1
    ],
    "대나무판자": [
        "은행나무판자",
        1,
        "대나무쪽",
        4
    ],
    "위로빗은수염": [
        "상급소나무판자",
        1,
        "중급아마천",
        2,
        "곡물가루",
        2
    ],
    "호랑이머리장식": [
        "중급은행나무판자",
        1,
        "구리조각",
        1,
        "청동결정",
        1,
        "호랑이가죽",
        20
    ],
    "단풍나무판자": [
        "대나무판자",
        1,
        "단풍통나무",
        5
    ],
    "아저씨수염": [
        "중급대나무판자",
        2,
        "상급황동괴",
        1,
        "모시풀잎",
        1
    ],
    "파천투구": [
        "경원투구",
        1,
        "단풍나무판자",
        1,
        "상급청동괴",
        1,
        "파천의문장",
        1,
        "중급아마천",
        1,
        "살쾡이왕의가죽",
        1
    ],
    "떡갈나무판자": [
        "단풍나무판자",
        1,
        "떡갈통나무",
        5
    ],
    "선장수염": [
        "떡갈나무판자",
        2,
        "상급아마천",
        1,
        "선장수염뭉치",
        1,
        "해마꼬리",
        1
    ],
    "한시등": [
        "중급단풍나무판자",
        2,
        "중급철괴",
        1,
        "아교",
        1
    ],
    "반송판자": [
        "떡갈나무판자",
        1,
        "반송쪽",
        5
    ],
    "갓": [
        "중급무명천",
        2,
        "중급떡갈나무판자",
        2,
        "연옥가루",
        1,
        "철가루",
        1,
        "도삭산살쾡이가죽",
        1
    ],
    "전모": [
        "중급무명천",
        2,
        "중급강철괴",
        2,
        "청옥가루",
        1,
        "적옥가루",
        1,
        "도삭산악어비늘",
        1
    ],
    "금강송판자": [
        "반송판자",
        1,
        "금강송쪽",
        5
    ],
    "금강투구": [
        "파천투구",
        1,
        "금강송판자",
        2,
        "상급떡갈나무판자",
        2,
        "금강의문장",
        1,
        "양가죽",
        1,
        "매의깃털",
        1
    ],
    "백송판자": [
        "금강송판자",
        1,
        "백송쪽",
        5
    ],
    "긴수염": [
        "중급금강송판자",
        2,
        "백옥",
        2,
        "산양삼잎",
        2,
        "은가루",
        1,
        "강시의손톱",
        1
    ],
    "금촛대": [
        "백송판자",
        2,
        "강철쇠조각",
        2,
        "황동촛등",
        1,
        "금가루",
        1,
        "아교",
        1
    ],
    "황금송판자": [
        "백송판자",
        1,
        "황금송쪽",
        5
    ],
    "바람제일식투구": [
        "금강투구",
        1,
        "황금송판자",
        2,
        "바람의문장",
        1,
        "상급은괴",
        3,
        "황금구슬",
        1,
        "백옥",
        1
    ],
    "묵철판자": [
        "상급황금송판자",
        1,
        "묵철가루",
        3
    ],
    "황금촛대": [
        "녹황금송쪽",
        5,
        "상급금괴",
        5,
        "고운금가루",
        5,
        "아교",
        10
    ],
    "바람제영식투구": [
        "바람홍옥투구",
        1,
        "묵철판자",
        3,
        "홍염의결정",
        3,
        "태풍의문장",
        1
    ],
    "연옥": [
        "연옥석",
        2
    ],
    "돌촉": [
        "단단한돌",
        2,
        "연옥",
        1
    ],
    "황동괴": [
        "연옥",
        2,
        "황동석",
        2
    ],
    "연옥노리개": [
        "연옥",
        3,
        "빛나는돌가루",
        1,
        "황마실",
        1
    ],
    "청동괴": [
        "황동괴",
        1,
        "청동석",
        3
    ],
    "황옥": [
        "연옥",
        3,
        "황옥석",
        3
    ],
    "구리패": [
        "구리조각",
        2,
        "청동결정",
        1,
        "모시실",
        2,
        "당귀가루",
        1
    ],
    "황옥노리개": [
        "연옥노리개",
        1,
        "황옥",
        2,
        "청동결정",
        1,
        "아마실",
        3,
        "연옥",
        2
    ],
    "구리조각": [
        "청동괴",
        1,
        "황동결정",
        1
    ],
    "적옥": [
        "황옥",
        1,
        "적옥석",
        5
    ],
    "철괴": [
        "구리조각",
        1,
        "철광석",
        5
    ],
    "적옥노리개": [
        "황옥노리개",
        1,
        "적옥",
        2,
        "상급모시천",
        1,
        "상급황동괴",
        1
    ],
    "강철괴": [
        "철괴",
        1,
        "철광결정",
        1
    ],
    "강철패": [
        "구리패",
        1,
        "강철쇠조각",
        2,
        "상급청동괴",
        1,
        "상급모시천",
        1,
        "양모실",
        1
    ],
    "강철쇠조각": [
        "강철괴",
        1,
        "철광결정",
        1
    ],
    "청옥": [
        "적옥",
        1,
        "연옥",
        1,
        "청옥석",
        5
    ],
    "은괴": [
        "강철쇠조각",
        1,
        "은광석",
        5
    ],
    "청옥노리개": [
        "적옥노리개",
        1,
        "청옥",
        2,
        "상급강철괴",
        1,
        "상급무명천",
        1,
        "중급대나무판자",
        1,
        "거미의이빨",
        2
    ],
    "은장패": [
        "강철패",
        1,
        "은조각",
        2,
        "산장뇌삼약제",
        2,
        "목화잎",
        2,
        "붉은실",
        2,
        "물소뿔",
        1
    ],
    "은조각": [
        "은괴",
        1,
        "은광결정",
        1
    ],
    "백옥": [
        "청옥",
        1,
        "연옥",
        1,
        "백옥석",
        5
    ],
    "금괴": [
        "은조각",
        1,
        "금광석",
        5
    ],
    "강철조각": [
        "강철괴",
        1,
        "은광결정",
        1
    ],
    "황금조각": [
        "금괴",
        1,
        "은광결정",
        1
    ],
    "백옥노리개": [
        "청옥노리개",
        1,
        "백옥",
        3,
        "상급비단",
        2,
        "황금보주",
        1,
        "황금구슬",
        1,
        "크리스탈",
        1
    ],
    "금장패": [
        "황금조각",
        2,
        "상급금강송판자",
        3,
        "황금보주",
        1,
        "황금구슬",
        1,
        "적옥",
        1
    ],
    "찬란한금괴": [
        "상급금괴",
        1,
        "홍염의결정",
        3
    ],
    "금옥노리개": [
        "백옥노리개",
        1,
        "황금비단",
        2,
        "고운금가루",
        30
    ],
    "금장신패": [
        "금장패",
        1,
        "황금비단",
        2,
        "홍염의결정",
        10
    ],
    "곡물가루": [
        "보리가루",
        1,
        "흰쌀가루",
        1,
        "밀가루",
        1
    ],
    "주먹밥": [
        "곡물가루",
        2,
        "굵은소금",
        1,
        "밀가루",
        1
    ],
    "독가루": [
        "독버섯",
        2,
        "뱀독",
        3,
        "곡물가루",
        2
    ],
    "쑥절편": [
        "쑥",
        2,
        "곡물가루",
        3,
        "삼나무잎",
        1,
        "숲돼지고기",
        5
    ],
    "맹독가루": [
        "맹독버섯",
        3,
        "뱀독",
        3,
        "독가루",
        1
    ],
    "수면제": [
        "수면가루",
        1,
        "독가루",
        1,
        "곡물가루",
        1
    ],
    "작약보혈탕": [
        "작약",
        4,
        "구리조각",
        2,
        "감초썬것",
        1
    ],
    "익기탕": [
        "당귀",
        4,
        "황옥",
        2,
        "곡물가루",
        1,
        "녹용가루",
        1
    ],
    "인삼약제": [
        "어린인삼",
        5,
        "곡물가루",
        5,
        "더덕가루",
        1
    ],
    "해독제": [
        "인삼약제",
        2,
        "대나무잎",
        2,
        "황기썬것",
        1,
        "연옥",
        2
    ],
    "영지약제": [
        "인삼약제",
        1,
        "영지버섯",
        5
    ],
    "청심환": [
        "영지약제",
        2,
        "상급모시천",
        1,
        "잎사귀가루",
        1,
        "인어의심장",
        1
    ],
    "인영보혈탕": [
        "영지약제",
        2,
        "적옥",
        1,
        "모시풀잎",
        2,
        "문어의심장",
        1
    ],
    "산인삼약제": [
        "영지약제",
        1,
        "산인삼",
        5
    ],
    "우황청심환": [
        "산인삼약제",
        2,
        "도삭산묘피",
        1,
        "청옥가루",
        1,
        "상급화살나무판자",
        1
    ],
    "삼기탕": [
        "산인삼약제",
        2,
        "적옥",
        1,
        "상급삼베천",
        1,
        "철가루",
        2,
        "코뿔소발톱",
        5
    ],
    "산양삼약제": [
        "산인삼약제",
        1,
        "산양삼",
        5
    ],
    "산양기탕": [
        "산양삼약제",
        2,
        "중급양모천",
        2,
        "황기썬것",
        1,
        "자현목",
        1
    ],
    "반하보혈탕": [
        "산양삼약제",
        2,
        "양가죽",
        1,
        "청옥",
        2,
        "황기썬것",
        1,
        "백현목",
        1
    ],
    "산장뇌삼약제": [
        "산양삼약제",
        1,
        "산장뇌삼",
        5
    ],
    "보중청심환": [
        "산장뇌삼약제",
        2,
        "백옥",
        2,
        "반송잎",
        2,
        "은광결정",
        2,
        "물소뿔",
        1
    ],
    "도삭산용기름": [
        "도삭산용고기",
        10,
        "금강의문장",
        1
    ],
    "천뇌삼약제": [
        "산장뇌삼약제",
        1,
        "천뇌삼",
        5
    ],
    "천강청심환": [
        "천뇌삼약제",
        3,
        "은조각",
        2,
        "금광결정",
        2,
        "운모",
        1
    ],
    "신비의용기름": [
        "도삭산용기름",
        1,
        "환혼의물약",
        3
    ],
    "신수경험치축복영약": [
        "묵광석결정",
        150,
        "만뇌삼",
        150
    ],
    "환수경험치축복영약": [
        "금화잎",
        150,
        "만뇌삼",
        150
    ],
    "불사의환단": [
        "녹황금송잎",
        30,
        "묵광석",
        50,
        "만천삼잎",
        50
    ],
    "최대체력증가영약": [
        "녹황금송잎",
        150,
        "금화잎",
        50
    ],
    "최대마력증가영약": [
        "녹황금송잎",
        150,
        "만뇌삼",
        50
    ],
    "미투리": [
        "새끼줄",
        1,
        "쇠고기",
        3,
        "연옥",
        1
    ],
    "갈모": [
        "새끼줄",
        1,
        "삼베실",
        1,
        "뱀고기",
        3
    ],
    "도롱이": [
        "새끼줄",
        2,
        "쪽잎",
        1,
        "담비고기",
        3
    ],
    "사슴뿔": [
        "중급삼베천",
        1,
        "쪽잎",
        1,
        "녹용",
        10
    ],
    "경원갑옷": [
        "중급황저포",
        1,
        "황동가루",
        1,
        "경원의문장",
        1,
        "여우모피",
        5
    ],
    "경원갑주": [
        "중급황저포",
        1,
        "연옥가루",
        1,
        "경원의문장",
        1,
        "여우모피",
        5
    ],
    "화관": [
        "아마실",
        3,
        "쪽꽃",
        1,
        "소나무잎",
        1,
        "상급새끼줄",
        2
    ],
    "꽃장식남자갑옷": [
        "아마천",
        1,
        "꽃장식",
        1,
        "연두색남자갑옷",
        1,
        "황동괴",
        1
    ],
    "꽃장식여자갑옷": [
        "아마천",
        1,
        "꽃장식",
        1,
        "연두색여자갑주",
        1,
        "황동괴",
        1
    ],
    "족두리": [
        "중급황저포",
        1,
        "은행나무판자",
        1,
        "황동결정",
        1
    ],
    "호박비녀족두리": [
        "모시천",
        1,
        "중급청동괴",
        1,
        "호박",
        3
    ],
    "추사체족자": [
        "상급황저포",
        1,
        "대나무판자",
        1,
        "중급새끼줄",
        1,
        "아교",
        1
    ],
    "해바라기화관": [
        "모시천",
        1,
        "해바라기꽃장식",
        2,
        "상급황동괴",
        1
    ],
    "파천갑옷": [
        "경원갑옷",
        1,
        "모시천",
        2,
        "상급황동괴",
        1,
        "파천의문장",
        1,
        "당귀잎",
        1,
        "복어의심장",
        1
    ],
    "파천갑주": [
        "경원갑주",
        1,
        "모시천",
        2,
        "상급소나무판자",
        1,
        "파천의문장",
        1,
        "작약잎",
        1,
        "복어의심장",
        1
    ],
    "묵죽도족자": [
        "상급모시천",
        2,
        "단풍나무판자",
        1
    ],
    "적향의환희": [
        "무명천",
        2,
        "상급대나무판자",
        1,
        "철광결정",
        2,
        "인어의심장",
        3
    ],
    "청향의환유": [
        "무명천",
        2,
        "상급대나무판자",
        1,
        "철광결정",
        2,
        "문어의심장",
        3
    ],
    "금테족두리": [
        "중급무명천",
        2,
        "강철쇠조각",
        1,
        "백두목황금잎",
        2
    ],
    "풍류진향": [
        "양모천",
        2,
        "상급철괴",
        1,
        "적옥",
        1,
        "어린인삼잎",
        1,
        "도삭산코뿔소발톱",
        2
    ],
    "풍류인향": [
        "양모천",
        2,
        "상급단풍나무판자",
        1,
        "적옥",
        1,
        "영지버섯",
        1,
        "도삭산코뿔소이빨",
        2
    ],
    "금강산도족자": [
        "비단",
        2,
        "금강송판자",
        2,
        "아교",
        1
    ],
    "금강갑옷": [
        "파천갑옷",
        1,
        "중급양모천",
        2,
        "상급떡갈나무판자",
        2,
        "금강의문장",
        1,
        "황옥",
        1,
        "산소괴왕의뿔",
        1
    ],
    "금강갑주": [
        "파천갑주",
        1,
        "중급양모천",
        2,
        "상급강철괴",
        2,
        "금강의문장",
        1,
        "황옥",
        1,
        "산소괴왕의뿔",
        1
    ],
    "검정비녀족두리": [
        "상급양모천",
        2,
        "은조각",
        2,
        "금강송잎",
        1,
        "백옥가루",
        1
    ],
    "삼화청랑": [
        "상급양모천",
        2,
        "중급금강송판자",
        2,
        "황옥",
        1,
        "붉은실",
        1,
        "녹류산신의털",
        1
    ],
    "삼화홍랑": [
        "중급비단",
        2,
        "상급반송판자",
        2,
        "적옥",
        1,
        "붉은실",
        1,
        "적류산신의털",
        1
    ],
    "황금비녀족두리": [
        "상급양모천",
        3,
        "황금송판자",
        2,
        "연옥",
        2,
        "금가루",
        2
    ],
    "바람제일식갑옷": [
        "금강갑옷",
        1,
        "상급비단",
        3,
        "상급금강송판자",
        3,
        "바람의문장",
        1,
        "붉은실",
        2,
        "황금보주",
        1
    ],
    "바람제일식갑주": [
        "금강갑옷",
        1,
        "상급비단",
        3,
        "상급금강송판자",
        3,
        "바람의문장",
        1,
        "붉은실",
        2,
        "황금보주",
        1
    ],
    "바람제영식갑옷": [
        "바람홍옥갑옷",
        1,
        "황금비단",
        3,
        "찬란한금괴",
        3,
        "묵철판자",
        3,
        "태풍의문장",
        1
    ],
    "바람제영식갑주": [
        "바람홍옥갑주",
        1,
        "황금비단",
        3,
        "찬란한금괴",
        3,
        "묵철판자",
        3,
        "태풍의문장",
        1
    ],
    "황동촛등": [
        "화살나무판자",
        1,
        "새끼줄",
        1,
        "쥐고기",
        3
    ],
    "돌화살통": [
        "화살나무판자",
        1,
        "돌촉",
        2,
        "박쥐고기",
        3
    ],
    "삿갓": [
        "중급화살나무판자",
        1,
        "쪽잎",
        1,
        "중급새끼줄",
        1
    ],
    "경원방패": [
        "중급황동괴",
        1,
        "경원의문장",
        1,
        "빛나는돌가루",
        1,
        "숲돼지고기",
        5
    ],
    "경원고서": [
        "중급황동괴",
        1,
        "경원의문장",
        1,
        "빛나는돌가루",
        1,
        "숲돼지고기",
        5
    ],
    "경원신부": [
        "중급황동괴",
        1,
        "경원의문장",
        1,
        "빛나는돌가루",
        1,
        "숲돼지고기",
        5
    ],
    "토끼귀": [
        "아마천",
        1,
        "상급새끼줄",
        2,
        "연옥",
        1,
        "토끼고기",
        20
    ],
    "작은창문": [
        "은행나무판자",
        1,
        "중급황동괴",
        1,
        "아교",
        1
    ],
    "양눈창문": [
        "중급소나무판자",
        1,
        "청동괴",
        1,
        "아교",
        1
    ],
    "작은대나무발": [
        "상급소나무판자",
        2,
        "중급새끼줄",
        2,
        "아교",
        1
    ],
    "죽제고비": [
        "중급은행나뭎나자",
        1,
        "구리조각",
        1,
        "아교",
        1
    ],
    "죽장함": [
        "대나무판자",
        1,
        "상급황동괴",
        1,
        "연옥",
        1,
        "아교",
        1
    ],
    "죽원방패": [
        "경원방패",
        1,
        "대나무판자",
        1,
        "중급청동괴",
        1,
        "쪽잎",
        1,
        "더덕잎",
        1
    ],
    "죽원고서": [
        "경원고서",
        1,
        "대나무판자",
        1,
        "중급청동괴",
        1,
        "쪽잎",
        1,
        "더덕잎",
        1
    ],
    "죽원신부": [
        "경원고서",
        1,
        "대나무판자",
        1,
        "중급청동괴",
        1,
        "쪽잎",
        1,
        "더덕잎",
        1
    ],
    "사각창문": [
        "중급은행나무판자",
        2,
        "중급대나무판자",
        1,
        "아교",
        1,
        "상급새끼줄",
        1
    ],
    "파천방패": [
        "죽원방패",
        1,
        "단풍나무판자",
        1,
        "상급아마천",
        1,
        "파천의문장",
        "중급청동괴",
        1,
        "살쾡이왕의가죽",
        1
    ],
    "파천고서": [
        "죽원고서",
        1,
        "단풍나무판자",
        1,
        "상급아마천",
        1,
        "파천의문장",
        "중급청동괴",
        1,
        "살쾡이왕의가죽",
        1
    ],
    "파천신부": [
        "죽원신부",
        1,
        "단풍나무판자",
        1,
        "상급아마천",
        1,
        "파천의문장",
        "중급청동괴",
        1,
        "살쾡이왕의가죽",
        1
    ],
    "하루기른수염": [
        "중급단풍나무판자",
        2,
        "강철괴",
        1,
        "어린인삼잎",
        1,
        "은여우털",
        1
    ],
    "산타수염": [
        "떡갈나무판자",
        2,
        "산타수염뭉치",
        1,
        "상급모시천",
        1,
        "너구리털",
        1
    ],
    "삼층책장": [
        "상급대나무판자",
        2,
        "구리조각",
        2,
        "아교",
        1
    ],
    "산양뿔": [
        "양모천",
        2,
        "산양뿔조각",
        1,
        "청옥",
        1,
        "목화잎",
        2
    ],
    "반닫이": [
        "반송판자",
        2,
        "중급떡갈나무판자",
        1,
        "아교",
        1,
        "상급새끼줄",
        1
    ],
    "연상": [
        "반송판자",
        2,
        "상급단풍나무판자",
        1,
        "중급황동괴",
        1,
        "아교",
        1
    ],
    "육각창문": [
        "중급반송판자",
        2,
        "중급떡갈나무판자",
        2,
        "아교",
        1
    ],
    "삼층장": [
        "금강송판자",
        2,
        "강철쇠조각",
        2,
        "아교",
        1
    ],
    "금강방패": [
        "파천방패",
        1,
        "금강송판자",
        2,
        "상급강철괴",
        2,
        "금강의문장",
        1,
        "양가죽",
        1,
        "물소뿔",
        1
    ],
    "금강고서": [
        "파천고서",
        1,
        "금강송판자",
        2,
        "상급강철괴",
        2,
        "금강의문장",
        1,
        "양가죽",
        1,
        "물소뿔",
        1
    ],
    "금강신부": [
        "파천신부",
        1,
        "금강송판자",
        2,
        "상급강철괴",
        2,
        "금강의문장",
        1,
        "양가죽",
        1,
        "물소뿔",
        1
    ],
    "각게수리": [
        "상급반송판자",
        2,
        "중급은괴",
        2,
        "상급아마천",
        1,
        "아교",
        1,
        "산양삼잎",
        2
    ],
    "2단문갑": [
        "백송판자",
        2,
        "중급은괴",
        2,
        "은광결정",
        1,
        "아교",
        1
    ],
    "루비왕관": [
        "은조각",
        2,
        "루비",
        1,
        "중급비단",
        2,
        "백옥석",
        2
    ],
    "빗접": [
        "상급금강송판자",
        3,
        "황금조각",
        2,
        "금가루",
        1,
        "아교",
        1,
        "은가루",
        1
    ],
    "바람제일식방패": [
        "금강방패",
        1,
        "황금송판자",
        2,
        "상급은괴",
        3,
        "바람의문장",
        1,
        "백옥",
        1,
        "연황금구슬",
        1
    ],
    "바람제일식고서": [
        "금강고서",
        1,
        "황금송판자",
        2,
        "상급은괴",
        3,
        "바람의문장",
        1,
        "백옥",
        1,
        "연황금구슬",
        1
    ],
    "바람제일식신부": [
        "금강신부",
        1,
        "황금송판자",
        2,
        "상급은괴",
        3,
        "바람의문장",
        1,
        "백옥",
        1,
        "연황금구슬",
        1
    ],
    "바람제영식방패": [
        "바람홍옥방패",
        1,
        "묵철가루",
        5,
        "찬란한금괴",
        3,
        "묵철판자",
        3,
        "태풍의문장",
        1
    ],
    "바람제영식고서": [
        "바람홍옥고서",
        1,
        "신비의용기름",
        3,
        "찬란한금괴",
        3,
        "환혼의물약",
        5,
        "태풍의문장",
        1
    ],
    "바람제영식신부": [
        "제작 불가",
        1
    ],
    "돌단검": [
        "돌촉",
        1,
        "화살통나무",
        1,
        "새끼줄",
        1
    ],
    "돌창": [
        "돌촉",
        1,
        "삼통나무",
        1,
        "새끼줄",
        1
    ],
    "경원비검": [
        "황동괴",
        1,
        "황마잎",
        1,
        "경원의문장",
        1,
        "호랑이가죽",
        5
    ],
    "경원비도": [
        "황동괴",
        1,
        "인진쑥",
        1,
        "경원의문장",
        1,
        "호랑이가죽",
        5
    ],
    "경원비봉": [
        "황동괴",
        1,
        "황마잎",
        1,
        "경원의문장",
        1,
        "호랑이가죽",
        5
    ],
    "경원비곤": [
        "황동괴",
        1,
        "인진쑥",
        1,
        "경원의문장",
        1,
        "호랑이가죽",
        5
    ],
    "경원비궁": [
        "황동괴",
        1,
        "소나무잎",
        1,
        "경원의문장",
        1,
        "호랑이가죽",
        5
    ],
    "경원비포": [
        "황동괴",
        1,
        "황마잎",
        1,
        "경원의문장",
        1,
        "호랑이가죽",
        5
    ],
    "경원비단봉": [
        "황동괴",
        1,
        "인진쑥",
        1,
        "경원의문장",
        1,
        "호랑이가죽",
        5
    ],
    "경원비장": [
        "황동괴",
        1,
        "인진쑥",
        1,
        "경원의문장",
        1,
        "호랑이가죽",
        5
    ],
    "경원비명도": [
        "황동괴",
        1,
        "황마잎",
        1,
        "경원의문장",
        1,
        "호랑이가죽",
        5
    ],
    "경원비겸": [
        "황동괴",
        1,
        "황마잎",
        1,
        "경원의문장",
        1,
        "호랑이가죽",
        5
    ],
    "금테머리띠": [
        "아마천",
        1,
        "중급황동괴",
        1,
        "백두목황금잎",
        1
    ],
    "깃발1": [
        "청동괴",
        1,
        "중급황저포",
        1,
        "아교",
        1
    ],
    "호박머리띠": [
        "모시천",
        1,
        "중급청동괴",
        1,
        "호박",
        3,
        "이리의송곳니",
        1
    ],
    "청동단검": [
        "중급황저포",
        1,
        "단단한돌가루",
        3,
        "흑담비가죽",
        1
    ],
    "청동장검": [
        "구리조각",
        1,
        "황옥가루",
        2,
        "중급아마천",
        1,
        "흑담비가죽",
        1
    ],
    "청동명궁": [
        "중급청동괴",
        1,
        "더덕가루",
        2,
        "중급은행나무판자",
        1,
        "흑담비가죽",
        1
    ],
    "파천비검": [
        "경원비검",
        1,
        "철괴",
        1,
        "중급아마천",
        2,
        "파천의문장",
        1,
        "청동결정",
        1,
        "원숭이털",
        2
    ],
    "파천비도": [
        "경원비도",
        1,
        "구리조각",
        1,
        "중급은행나무판자",
        2,
        "파천의문장",
        1,
        "청동결정",
        1,
        "원숭이털",
        2
    ],
    "파천비봉": [
        "경원비봉",
        1,
        "철괴",
        1,
        "중급은행나무판자",
        2,
        "파천의문장",
        1,
        "모시풀잎",
        1,
        "코뿔소발톱",
        5
    ],
    "파천비곤": [
        "경원비곤",
        1,
        "구리조각",
        1,
        "중급아마천",
        2,
        "파천의문장",
        1,
        "모시풀잎",
        1,
        "코뿔소발톱",
        5
    ],
    "파천비궁": [
        "경원비궁",
        1,
        "철괴",
        1,
        "중급청동괴",
        2,
        "파천의문장",
        1,
        "대나무잎",
        1,
        "코뿔소발톱",
        5
    ],
    "파천비포": [
        "경원비포",
        1,
        "철괴",
        1,
        "중급은행나무판자",
        2,
        "파천의문장",
        1,
        "모시풀잎",
        1,
        "코뿔소발톱",
        5
    ],
    "파천비단봉": [
        "경원비단봉",
        1,
        "구리조각",
        1,
        "중급아마천",
        2,
        "파천의문장",
        1,
        "모시풀잎",
        1,
        "코뿔소발톱",
        5
    ],
    "파천비장": [
        "경원비장",
        1,
        "구리조각",
        1,
        "중급아마천",
        2,
        "파천의문장",
        1,
        "모시풀잎",
        1,
        "코뿔소발톱",
        5
    ],
    "파천비명도": [
        "경원비명도",
        1,
        "철괴",
        1,
        "중급은행나무판자",
        2,
        "파천의문장",
        1,
        "모시풀잎",
        1,
        "코뿔소발톱",
        5
    ],
    "파천비겸": [
        "경원비겸",
        1,
        "철괴",
        1,
        "중급은행나무판자",
        2,
        "파천의문장",
        1,
        "모시풀잎",
        1,
        "코뿔소발톱",
        5
    ],
    "홍실쌍검자식": [
        "강철괴",
        2,
        "중급단풍나무판자",
        1,
        "철검",
        1,
        "아교",
        1
    ],
    "오공머리띠": [
        "떡갈나무판자",
        2,
        "상급황저포",
        1,
        "철광결정",
        1,
        "원숭이털",
        1
    ],
    "오색머리띠": [
        "중급무명천",
        2,
        "강철쇠조각",
        1,
        "청옥가루",
        1,
        "적옥가루",
        1
    ],
    "강철단검": [
        "강철괴",
        2,
        "반송판자",
        1,
        "상급새끼줄",
        2,
        "거미의이빨",
        3
    ],
    "강철장검": [
        "강철괴",
        2,
        "양모천",
        1,
        "상급새끼줄",
        2,
        "거미의이빨",
        3
    ],
    "강철명궁": [
        "강철괴",
        2,
        "산인삼약제",
        1,
        "상급삼베천",
        1,
        "거미의이빨",
        3
    ],
    "금강비검": [
        "파천비검",
        1,
        "은괴",
        2,
        "중급비단",
        2,
        "금강의문장",
        1,
        "도삭산묘피",
        2
    ],
    "금강비도": [
        "파천비도",
        1,
        "은괴",
        2,
        "중급금강송판자",
        2,
        "금강의문장",
        1,
        "매의깃털",
        1
    ],
    "금강비봉": [
        "파천비봉",
        1,
        "중급강철괴",
        2,
        "중급비단",
        2,
        "금강의문장",
        1,
        "황옥",
        1,
        "도삭산묘피",
        2
    ],
    "금강비곤": [
        "파천비곤",
        1,
        "중급강철괴",
        2,
        "중급양모천",
        2,
        "금강의문장",
        1,
        "적옥",
        1,
        "매의깃털",
        1
    ],
    "금강비궁": [
        "파천비궁",
        1,
        "은괴",
        2,
        "중급금강송판자",
        2,
        "금강의문장",
        1,
        "양가죽",
        2,
        "도삭산묘피",
        2
    ],
    "금강비포": [
        "파천비포",
        1,
        "중급강철괴",
        2,
        "중급비단",
        2,
        "금강의문장",
        1,
        "황옥",
        1,
        "도삭산묘피",
        2
    ],
    "금강비단봉": [
        "파천비단봉",
        1,
        "중급강철괴",
        2,
        "중급양모천",
        2,
        "금강의문장",
        1,
        "적옥",
        1,
        "매의깃털",
        1
    ],
    "금강비장": [
        "파천비장",
        1,
        "중급강철괴",
        2,
        "중급양모천",
        2,
        "금강의문장",
        1,
        "적옥",
        1,
        "매의깃털",
        1
    ],
    "금강비명도": [
        "파천비명도",
        1,
        "중급강철괴",
        2,
        "중급양모천",
        2,
        "금강의문장",
        1,
        "적옥",
        1,
        "매의깃털",
        1
    ],
    "금강비겸": [
        "파천비겸",
        1,
        "중급강철괴",
        2,
        "중급비단",
        2,
        "금강의문장",
        1,
        "황옥",
        1,
        "도삭산묘피",
        2
    ],
    "철투구장식": [
        "백송판자",
        2,
        "상급강철괴",
        2,
        "초록색남자투구",
        1,
        "초록색여자투구",
        1,
        "아교",
        1
    ],
    "선녀머리띠": [
        "중급비단",
        2,
        "은조각",
        2,
        "붉은실",
        2,
        "적류산신의털",
        1,
        "녹류산신의털",
        1
    ],
    "갑옷장식1": [
        "중급금강송판자",
        2,
        "중급은괴",
        2,
        "구리남자갑주",
        1,
        "구리여자갑주",
        1,
        "아교",
        1
    ],
    "빛나는갑옷장식": [
        "갑옷장식1",
        "상급금괴",
        5,
        "묵광석결정",
        3,
        "아교",
        10
    ],
    "차원의덫": [
        "어둠의보주",
        1,
        "아난타의이빨",
        2,
        "금강의문장",
        1
    ],
    "바람제일식검": [
        "금강비검",
        1,
        "상급은괴",
        3,
        "상급금강송판자",
        3,
        "바람의문장",
        1,
        "백옥가루",
        2,
        "황금보주",
        1
    ],
    "바람제일식도": [
        "금강비도",
        1,
        "상급은괴",
        3,
        "상급비단",
        3,
        "바람의문장",
        1,
        "금가루",
        1,
        "연황금보주",
        1
    ],
    "바람제일식봉": [
        "금강비봉",
        1,
        "상급금강송판자",
        3,
        "상급은괴",
        3,
        "바람의문장",
        1,
        "백옥가루",
        2,
        "황금보주",
        1
    ],
    "바람제일식곤": [
        "금강비곤",
        1,
        "상급금강송판자",
        3,
        "상급비단",
        3,
        "바람의문장",
        1,
        "금가루",
        1,
        "연황금보주",
        1
    ],
    "바람제일식궁": [
        "금강비궁",
        1,
        "중급금괴",
        3,
        "상급금강송판자",
        3,
        "바람의문장",
        1,
        "은가루",
        2,
        "황금보주",
        1
    ],
    "바람제일식포": [
        "금강비포",
        1,
        "상급금강송판자",
        3,
        "상급은괴",
        3,
        "바람의문장",
        1,
        "백옥가루",
        2,
        "황금보주",
        1
    ],
    "바람제일식단봉": [
        "금강비단봉",
        1,
        "상급금강송판자",
        3,
        "상급비단",
        3,
        "바람의문장",
        1,
        "금가루",
        1,
        "연황금보주",
        1
    ],
    "바람제일식장": [
        "금강비장",
        1,
        "상급금강송판자",
        3,
        "상급비단",
        3,
        "금가루",
        1,
        "연황금보주",
        1,
        "바람의문장",
        1
    ],
    "바람제일식명도": [
        "금강비명도",
        1,
        "상급금강송판자",
        3,
        "상급은괴",
        3,
        "백옥가루",
        2,
        "황금보주",
        1,
        "바람의문장",
        1
    ],
    "바람제일식겸": [
        "금강비겸",
        1,
        "상급금강송판자",
        3,
        "상급은괴",
        3,
        "백옥가루",
        2,
        "황금보주",
        1,
        "바람의문장",
        1
    ],
    "바람제영식검": [
        "바람태사검",
        1,
        "태풍의문장",
        1,
        "찬란한금괴",
        3,
        "묵철판자",
        3,
        "묵철가루",
        5,
        "환혼의물약",
        1
    ],
    "바람제영식도": [
        "바람태사도",
        1,
        "태풍의문장",
        1,
        "찬란한금괴",
        3,
        "묵철판자",
        3,
        "고운금가루",
        5,
        "홍염의결정",
        1
    ],
    "바람제영식봉": [
        "바람태사봉",
        1,
        "태풍의문장",
        1,
        "찬란한금괴",
        3,
        "황금비단",
        3,
        "홍염의결정",
        5,
        "환혼의물약",
        1
    ],
    "바람제영식곤": [
        "바람태사곤",
        1,
        "태풍의문장",
        1,
        "찬란한금괴",
        3,
        "황금비단",
        3,
        "묵철가루",
        5,
        "환혼의물약",
        1
    ],
    "바람제영식궁": [
        "바람태사궁",
        1,
        "태풍의문장",
        1,
        "찬란한금괴",
        3,
        "묵철판자",
        3,
        "고운금가루",
        5,
        "홍염의결정",
        1
    ],
    "바람제영식포": [
        "바람태사포",
        1,
        "태풍의문장",
        1,
        "찬란한금괴",
        3,
        "황금비단",
        3,
        "홍염의결정",
        5,
        "환혼의물약",
        1
    ],
    "바람제영식단봉": [
        "바람태사단봉",
        1,
        "태풍의문장",
        1,
        "찬란한금괴",
        3,
        "황금비단",
        3,
        "묵철가루",
        5,
        "환혼의물약",
        1
    ],
    "바람제영식장": [
        "바람태사장",
        1,
        "태풍의문장",
        1,
        "찬란한금괴",
        3,
        "황금비단",
        3,
        "묵철가루",
        5,
        "환혼의물약",
        1
    ],
    "바람제영식명도": [
        "바람태사명도",
        1,
        "태풍의문장",
        1,
        "찬란한금괴",
        3,
        "황금비단",
        3,
        "홍염의결정",
        5,
        "환혼의물약",
        1
    ],
    "바람제영식겸": [
        "바람태사겸",
        1,
        "태풍의문장",
        1,
        "찬란한금괴",
        3,
        "황금비단",
        3,
        "홍염의결정",
        5,
        "환혼의물약",
        1
    ],
    "강화슬롯부적": [
        "연옥",
        1,
        "화살나무잎",
        2,
        "영혼의물약",
        1,
        "사슴고기",
        10
    ],
    "초급재료보호부적": [
        "곡물가루",
        2,
        "삼나무잎",
        2,
        "영혼의물약",
        1,
        "웅담",
        5
    ],
    "초급성공강화부적": [
        "인진쑥가루",
        1,
        "황마잎",
        2,
        "영혼의물약",
        1,
        "여우모피",
        5
    ],
    "초급공격강화부적": [
        "황동괴조각",
        1,
        "소나무잎",
        2,
        "영혼의물약",
        1,
        "뱀고기",
        10
    ],
    "초급방어강화부적": [
        "청동괴조각",
        1,
        "은행나무잎",
        2,
        "선혼의물약",
        1,
        "자호의가죽",
        10
    ],
    "초급명중강화부적": [
        "중급은행나무조각",
        1,
        "더덕잎",
        2,
        "선혼의물약",
        1,
        "황옥석",
        5
    ],
    "중급재료보호부적": [
        "작약말린것",
        1,
        "대나무잎",
        2,
        "선혼의물약",
        1,
        "여우모피",
        5
    ],
    "중급명중강화부적": [
        "주급대나무조각",
        4,
        "모시풀잎",
        2,
        "선혼의물약",
        1,
        "황옥석",
        5
    ],
    "중급공격강화부적": [
        "중급청동괴조각",
        1,
        "당귀잎",
        2,
        "선혼의물약",
        1,
        "은행통나무",
        5
    ],
    "중급성공강화부적": [
        "철괴조각",
        1,
        "어린인삼잎",
        3,
        "진혼의물약",
        1,
        "대나무쪽",
        5
    ],
    "초급필살강화부적": [
        "인삼약제",
        4,
        "단풍나무잎",
        3,
        "진혼의물약",
        1,
        "어린인삼",
        5
    ],
    "투구방어강화부적": [
        "중급모시천조각",
        1,
        "당귀잎",
        3,
        "진혼의물약",
        1,
        "적옥석",
        5
    ],
    "상급명중강화부적": [
        "중급떡갈나무조각",
        2,
        "목화잎",
        2,
        "진혼의물약",
        1,
        "철광석",
        5
    ],
    "상급공격강화부적": [
        "영지버섯말린것",
        2,
        "떡갈나무잎",
        2,
        "진혼의물약",
        1,
        "무명실",
        5
    ],
    "방패방어강화부적": [
        "중급양모천조각",
        2,
        "산인삼잎",
        2,
        "정혼의물약",
        1,
        "반송쪽",
        5,
        "인어의심장",
        1
    ],
    "중급필살강화부적": [
        "산인삼약제",
        4,
        "반송잎",
        2,
        "정혼의물약",
        1,
        "청옥석",
        5,
        "해마의심장",
        1
    ],
    "고급공격강화부적": [
        "중급비단조각",
        2,
        "금강송잎",
        2,
        "정혼의물약",
        1,
        "은광석",
        5,
        "강시의손톱",
        1
    ],
    "상급필살강화부적": [
        "산양삼약제",
        4,
        "목화잎",
        2,
        "정혼의물약",
        1,
        "금강송쪽",
        5,
        "도삭산살쾡이가죽",
        1
    ],
    "상급성공강화부적": [
        "은괴조각",
        2,
        "산양삼잎",
        2,
        "정혼의물약",
        1,
        "명주실",
        5,
        "산소괴왕의뿔",
        1
    ],
    "갑옷방어강화부적": [
        "백옥조각",
        2,
        "산장뇌삼잎",
        2,
        "천혼의물약",
        1,
        "백옥석",
        5,
        "강시의손톱",
        2
    ],
    "고급명중강화부적": [
        "중급백송조각",
        2,
        "홍화잎",
        2,
        "천혼의물약",
        1,
        "백송쪽",
        5,
        "매의깃털",
        2
    ],
    "고급필살강화부적": [
        "천뇌삼약제",
        4,
        "치자나무잎",
        2,
        "천혼의물약",
        1,
        "금광석",
        5,
        "토요지석",
        1
    ],
    "전설성공강화부적": [
        "최고성공강화부적",
        1,
        "녹황금송잎",
        2,
        "묵광석결정",
        3,
        "환혼의물약",
        5
    ],
    "전설공격강화부적": [
        "최고공격강화부적",
        1,
        "만천삼잎",
        2,
        "묵광석결정",
        3,
        "홍염의결정",
        5
    ],
    "전설필살강화부적": [
        "최고필살강화부적",
        1,
        "만천삼잎",
        2,
        "금화잎",
        3,
        "고운금가루",
        5
    ],
    "전설재료보호부적": [
        "최고재료보호부적",
        1,
        "만천삼잎",
        2,
        "녹황금송잎",
        2,
        "고운금가루",
        5
    ],
    "전설명중강화부적": [
        "최고명중강화부적",
        1,
        "녹황금송잎",
        2,
        "금화잎",
        3,
        "묵철가루",
        5
    ],
    "둔갑체력강화부적": [
        "금화꽃",
        30,
        "금화잎",
        5,
        "만뇌삼",
        50,
        "고운금가루",
        5,
        "묵철가루",
        5
    ],
    "둔갑마력강화부적": [
        "녹황금송쪽",
        30,
        "녹황금송잎",
        5,
        "만뇌삼",
        50,
        "홍염의결정",
        5,
        "환혼의물약",
        5
    ],
    "기절저항환약(하)": [
        "작약잎",
        1,
        "어린인삼",
        1,
        "곡물가루",
        1
    ],
    "침묵저항환약(하)": [
        "천뇌삼잎",
        1,
        "영지버섯",
        1,
        "곡물가루",
        1
    ],
    "속박저항환약(하)": [
        "아마잎",
        1,
        "송이버섯",
        1,
        "곡물가루",
        1
    ],
    "수면저항환약(하)": [
        "치자나무잎",
        1,
        "수면가루",
        1,
        "곡물가루",
        1
    ],
    "절망저항환약(하)": [
        "어린인삼잎",
        1,
        "감초썬것",
        1,
        "곡물가루",
        1
    ],
    "중독저항환약(하)": [
        "더덕잎",
        1,
        "독버섯",
        1,
        "곡물가루",
        1
    ],
    "마비저항환약(하)": [
        "당귀잎",
        1,
        "독버섯",
        1,
        "곡물가루",
        1
    ],
    "도발저항환약(하)": [
        "모시풀잎",
        1,
        "표고버섯",
        1,
        "곡물가루",
        1
    ],
    "기절저항환약(중)": [
        "작약잎",
        2,
        "어린인삼",
        2,
        "곡물가루",
        1
    ],
    "침묵저항환약(중)": [
        "천뇌삼잎",
        2,
        "영지버섯",
        2,
        "곡물가루",
        1
    ],
    "속박저항환약(중)": [
        "아마잎",
        2,
        "송이버섯",
        2,
        "곡물가루",
        1
    ],
    "수면저항환약(중)": [
        "치자나무잎",
        2,
        "수면가루",
        2,
        "곡물가루",
        1
    ],
    "절망저항환약(중)": [
        "어린인삼잎",
        2,
        "감초썬것",
        2,
        "곡물가루",
        1
    ],
    "중독저항환약(중)": [
        "더덕잎",
        2,
        "독버섯",
        2,
        "곡물가루",
        1
    ],
    "마비저항환약(중)": [
        "당귀잎",
        2,
        "독버섯",
        2,
        "곡물가루",
        1
    ],
    "도발저항환약(중)": [
        "모시풀잎",
        2,
        "표고버섯",
        2,
        "곡물가루",
        1
    ],
    "기절저항환약(상)": [
        "기절저항환약(중)",
        1,
        "사념의정수",
        1
    ],
    "침묵저항환약(상)": [
        "침묵저항환약(중)",
        1,
        "사념의정수",
        1
    ],
    "속박저항환약(상)": [
        "속박저항환약(중)",
        1,
        "사념의정수",
        1
    ],
    "수면저항환약(상)": [
        "수면저항환약(중)",
        1,
        "사념의정수",
        1
    ],
    "절망저항환약(상)": [
        "절망저항환약(중)",
        1,
        "사념의정수",
        1
    ],
    "중독저항환약(상)": [
        "중독저항환약(중)",
        1,
        "사념의정수",
        1
    ],
    "마비저항환약(상)": [
        "마비저항환약(중)",
        1,
        "사념의정수",
        1
    ],
    "도발저항환약(상)": [
        "도발저항환약(중)",
        1,
        "사념의정수",
        1
    ],
    "기절저항환약(특상)": [
        "기절저항환약(상)",
        1,
        "사념의정수",
        1
    ],
    "침묵저항환약(특상)": [
        "침묵저항환약(상)",
        1,
        "사념의정수",
        1
    ],
    "속박저항환약(특상)": [
        "속박저항환약(상)",
        1,
        "사념의정수",
        1
    ],
    "수면저항환약(특상)": [
        "수면저항환약(상)",
        1,
        "사념의정수",
        1
    ],
    "절망저항환약(특상)": [
        "절망저항환약(상)",
        1,
        "사념의정수",
        1
    ],
    "중독저항환약(특상)": [
        "중독저항환약(상)",
        1,
        "사념의정수",
        1
    ],
    "마비저항환약(특상)": [
        "마비저항환약(상)",
        1,
        "사념의정수",
        1
    ],
    "도발저항환약(특상)": [
        "도발저항환약(상)",
        1,
        "사념의정수",
        1
    ],
    "초급기절저항강화부적": [
        "인삼약제",
        5,
        "작약잎",
        1
    ],
    "초급침묵저항강화부적": [
        "청심환",
        1,
        "천뇌삼잎",
        1
    ],
    "초급속박저항강화부적": [
        "인삼약제",
        5,
        "아마잎",
        1
    ],
    "초급수면저항강화부적": [
        "수면가루",
        5,
        "치자나무잎",
        1
    ],
    "초급절망저항강화부적": [
        "인삼약제",
        5,
        "어린인삼잎",
        1
    ],
    "초급중독저항강화부적": [
        "독가루",
        5,
        "더덕잎",
        1
    ],
    "초급마비저항강화부적": [
        "독가루",
        5,
        "당귀잎",
        1
    ],
    "초급도발저항강화부적": [
        "청심환",
        1,
        "모시풀잎",
        1
    ],
    "중급기절저항강화부적": [
        "초급침묵저항강화부적",
        1,
        "인삼약제",
        1
    ],
    "중급침묵저항강화부적": [
        "초급침묵저항강화부적",
        1,
        "청심환",
        1
    ],
    "중급속박저항강화부적": [
        "초급속박저항강화부적",
        1,
        "인삼약제",
        1
    ],
    "중급수면저항강화부적": [
        "초급수면저항강화부적",
        1,
        "수면가루",
        1
    ],
    "중급절망저항강화부적": [
        "초급절망저항강화부적",
        1,
        "인삼약제",
        1
    ],
    "중급중독저항강화부적": [
        "초급중독저항강화부적",
        1,
        "독가루",
        1
    ],
    "중급마비저항강화부적": [
        "초급마비저항강화부적",
        1,
        "독가루",
        1
    ],
    "중급도발저항강화부적": [
        "초급도발저항강화부적",
        1,
        "청심환",
        1
    ],
    "상급기절저항강화부적": [
        "중급침묵저항강화부적",
        1,
        "사념의정수",
        1
    ],
    "상급침묵저항강화부적": [
        "중급침묵저항강화부적",
        1,
        "사념의정수",
        1
    ],
    "상급속박저항강화부적": [
        "중급속박저항강화부적",
        1,
        "사념의정수",
        1
    ],
    "상급수면저항강화부적": [
        "중급수면저항강화부적",
        1,
        "사념의정수",
        1
    ],
    "상급절망저항강화부적": [
        "중급절망저항강화부적",
        1,
        "사념의정수",
        1
    ],
    "상급중독저항강화부적": [
        "중급중독저항강화부적",
        1,
        "사념의정수",
        1
    ],
    "상급마비저항강화부적": [
        "중급마비저항강화부적",
        1,
        "사념의정수",
        1
    ],
    "상급도발저항강화부적": [
        "중급도발저항강화부적",
        1,
        "사념의정수",
        1
    ],
    "고급기절저항강화부적": [
        "상급침묵저항강화부적",
        1,
        "사념의정수",
        2
    ],
    "고급침묵저항강화부적": [
        "상급침묵저항강화부적",
        1,
        "사념의정수",
        2
    ],
    "고급속박저항강화부적": [
        "상급속박저항강화부적",
        1,
        "사념의정수",
        2
    ],
    "고급수면저항강화부적": [
        "상급수면저항강화부적",
        1,
        "사념의정수",
        2
    ],
    "고급절망저항강화부적": [
        "상급절망저항강화부적",
        1,
        "사념의정수",
        2
    ],
    "고급중독저항강화부적": [
        "상급중독저항강화부적",
        1,
        "사념의정수",
        2
    ],
    "고급마비저항강화부적": [
        "상급마비저항강화부적",
        1,
        "사념의정수",
        2
    ],
    "고급도발저항강화부적": [
        "상급도발저항강화부적",
        1,
        "사념의정수",
        2
    ],
    "최고기절저항강화부적": [
        "고급침묵저항강화부적",
        1,
        "사념의정수",
        3,
        "영령의조각",
        1
    ],
    "최고침묵저항강화부적": [
        "고급침묵저항강화부적",
        1,
        "사념의정수",
        3,
        "영령의조각",
        1
    ],
    "최고속박저항강화부적": [
        "고급속박저항강화부적",
        1,
        "사념의정수",
        3,
        "영령의조각",
        1
    ],
    "최고수면저항강화부적": [
        "고급수면저항강화부적",
        1,
        "사념의정수",
        3,
        "영령의조각",
        1
    ],
    "최고절망저항강화부적": [
        "고급절망저항강화부적",
        1,
        "사념의정수",
        3,
        "영령의조각",
        1
    ],
    "최고중독저항강화부적": [
        "고급중독저항강화부적",
        1,
        "사념의정수",
        3,
        "영령의조각",
        1
    ],
    "최고마비저항강화부적": [
        "고급마비저항강화부적",
        1,
        "사념의정수",
        3,
        "영령의조각",
        1
    ],
    "최고도발저항강화부적": [
        "고급도발저항강화부적",
        1,
        "사념의정수",
        3,
        "영령의조각",
        1
    ],
    "전설기절저항강화부적": [
        "최고침묵저항강화부적",
        1,
        "사념의정수",
        5,
        "영령의조각",
        3
    ],
    "전설침묵저항강화부적": [
        "최고침묵저항강화부적",
        1,
        "사념의정수",
        5,
        "영령의조각",
        3
    ],
    "전설속박저항강화부적": [
        "최고속박저항강화부적",
        1,
        "사념의정수",
        5,
        "영령의조각",
        3
    ],
    "전설수면저항강화부적": [
        "최고수면저항강화부적",
        1,
        "사념의정수",
        5,
        "영령의조각",
        3
    ],
    "전설절망저항강화부적": [
        "최고절망저항강화부적",
        1,
        "사념의정수",
        5,
        "영령의조각",
        3
    ],
    "전설중독저항강화부적": [
        "최고중독저항강화부적",
        1,
        "사념의정수",
        5,
        "영령의조각",
        3
    ],
    "전설마비저항강화부적": [
        "최고마비저항강화부적",
        1,
        "사념의정수",
        5,
        "영령의조각",
        3
    ],
    "전설도발저항강화부적": [
        "최고도발저항강화부적",
        1,
        "사념의정수",
        5,
        "영령의조각",
        3
    ]
}